low_cost_ecs/__init__.py
low_cost_ecs/py.typed
low_cost_ecs/_jsii/__init__.py
low_cost_ecs/_jsii/low-cost-ecs@0.0.188.jsii.tgz
low_cost_ecs-0.0.188.dist-info/LICENSE
low_cost_ecs-0.0.188.dist-info/METADATA
low_cost_ecs-0.0.188.dist-info/WHEEL
low_cost_ecs-0.0.188.dist-info/top_level.txt
low_cost_ecs-0.0.188.dist-info/RECORD
