Metadata-Version: 2.1
Name: low-cost-ecs
Version: 0.0.188
Summary: Easy and low-cost ECS on EC2 server without a load balancer
Home-page: https://github.com/rajyan/low-cost-ecs.git
Author: Yohta Kimura<kitakita7617@gmail.com>
License: MIT
Project-URL: Source, https://github.com/rajyan/low-cost-ecs.git
Classifier: Intended Audience :: Developers
Classifier: Operating System :: OS Independent
Classifier: Programming Language :: JavaScript
Classifier: Programming Language :: Python :: 3 :: Only
Classifier: Programming Language :: Python :: 3.9
Classifier: Programming Language :: Python :: 3.10
Classifier: Programming Language :: Python :: 3.11
Classifier: Typing :: Typed
Classifier: Development Status :: 4 - Beta
Classifier: License :: OSI Approved
Requires-Python: ~=3.9
License-File: LICENSE
Requires-Dist: aws-cdk-lib <3.0.0,>=2.37.0
Requires-Dist: constructs <11.0.0,>=10.0.5
Requires-Dist: jsii <2.0.0,>=1.125.0
Requires-Dist: publication >=0.0.3
Requires-Dist: typeguard ==2.13.3
